{"stats":{"minecraft:custom":{"minecraft:animals_bred":19,"minecraft:interact_with_crafting_table":99,"minecraft:leave_game":8,"minecraft:time_since_death":30238,"minecraft:sprint_one_cm":2712263,"minecraft:damage_blocked_by_shield":2440,"minecraft:drop":88,"minecraft:talked_to_villager":8,"minecraft:play_time":1171773,"minecraft:deaths":2,"minecraft:jump":11680,"minecraft:walk_on_water_one_cm":173146,"minecraft:enchant_item":5,"minecraft:interact_with_furnace":199,"minecraft:sleep_in_bed":45,"minecraft:damage_dealt":29850,"minecraft:crouch_one_cm":169483,"minecraft:interact_with_smoker":15,"minecraft:horse_one_cm":1671460,"minecraft:interact_with_smithing_table":1,"minecraft:interact_with_anvil":8,"minecraft:mob_kills":195,"minecraft:climb_one_cm":5948,"minecraft:walk_one_cm":3521939,"minecraft:sneak_time":51611,"minecraft:walk_under_water_one_cm":119633,"minecraft:interact_with_blast_furnace":23,"minecraft:total_world_time":1173695,"minecraft:pot_flower":10,"minecraft:interact_with_grindstone":1,"minecraft:interact_with_stonecutter":5,"minecraft:time_since_rest":30346,"minecraft:damage_taken":7332,"minecraft:swim_one_cm":297630,"minecraft:fly_one_cm":1708405,"minecraft:open_chest":905,"minecraft:fall_one_cm":208925},"minecraft:crafted":{"minecraft:grindstone":1,"minecraft:oak_planks":152,"minecraft:smooth_stone":73,"minecraft:blaze_powder":10,"minecraft:cooked_chicken":6,"minecraft:chain":20,"minecraft:stone":626,"minecraft:nether_brick":194,"minecraft:cooked_mutton":31,"minecraft:glass":197,"minecraft:chest":12,"minecraft:acacia_fence":102,"minecraft:ender_eye":5,"minecraft:stone_bricks":52,"minecraft:cooked_rabbit":1,"minecraft:golden_boots":1,"minecraft:smoker":1,"minecraft:item_frame":19,"minecraft:cooked_porkchop":15,"minecraft:crafting_table":4,"minecraft:acacia_slab":24,"minecraft:wooden_pickaxe":1,"minecraft:iron_helmet":1,"minecraft:gold_block":6,"minecraft:stone_brick_stairs":32,"minecraft:iron_chestplate":1,"minecraft:book":1,"minecraft:paper":3,"minecraft:diamond_pickaxe":5,"minecraft:emerald_block":1,"minecraft:shield":1,"minecraft:stone_slab":6,"minecraft:stick":236,"minecraft:iron_ingot":614,"minecraft:iron_pickaxe":7,"minecraft:iron_block":49,"minecraft:stone_sword":1,"minecraft:acacia_door":3,"minecraft:gold_ingot":52,"minecraft:shears":1,"minecraft:coal":9,"minecraft:stone_shovel":3,"minecraft:iron_nugget":837,"minecraft:furnace":23,"minecraft:blast_furnace":2,"minecraft:bone_meal":168,"minecraft:glass_pane":112,"minecraft:iron_axe":6,"minecraft:iron_hoe":2,"minecraft:stone_pickaxe":4,"minecraft:redstone_block":151,"minecraft:dark_oak_planks":4,"minecraft:wheat":477,"minecraft:cooked_beef":37,"minecraft:coal_block":8,"minecraft:crimson_planks":20,"minecraft:diamond_sword":1,"minecraft:enchanting_table":1,"minecraft:nether_bricks":55,"minecraft:cooked_salmon":7,"minecraft:bucket":1,"minecraft:acacia_stairs":16,"minecraft:stone_axe":1,"minecraft:glowstone":11,"minecraft:air":0,"minecraft:jungle_planks":8,"minecraft:iron_shovel":3,"minecraft:iron_leggings":1,"minecraft:stonecutter":1,"minecraft:white_bed":1,"minecraft:acacia_planks":624,"minecraft:torch":104,"minecraft:lapis_block":15},"minecraft:mined":{"minecraft:attached_melon_stem":4,"minecraft:stone_pressure_plate":1,"minecraft:white_bed":5,"minecraft:obsidian":5,"minecraft:cave_vines_plant":27,"minecraft:granite":114,"minecraft:budding_amethyst":2,"minecraft:acacia_log":160,"minecraft:grass_block":117,"minecraft:soul_soil":25,"minecraft:crimson_fungus":1,"minecraft:oxeye_daisy":8,"minecraft:nether_wart":30,"minecraft:spawner":1,"minecraft:weeping_vines_plant":32,"minecraft:magma_block":3,"minecraft:glowstone":14,"minecraft:iron_ore":483,"minecraft:cobbled_deepslate":2,"minecraft:fire":20,"minecraft:anvil":1,"minecraft:deepslate_lapis_ore":2,"minecraft:cave_vines":17,"minecraft:tripwire":5,"minecraft:deepslate_redstone_ore":62,"minecraft:cut_sandstone":22,"minecraft:medium_amethyst_bud":1,"minecraft:crimson_nylium":56,"minecraft:torch":42,"minecraft:light_gray_terracotta":64,"minecraft:calcite":89,"minecraft:poppy":1,"minecraft:chest":24,"minecraft:nether_quartz_ore":36,"minecraft:cobblestone":157,"minecraft:cyan_bed":1,"minecraft:oak_planks":28,"minecraft:sugar_cane":39,"minecraft:iron_door":4,"minecraft:wall_torch":46,"minecraft:amethyst_block":20,"minecraft:white_terracotta":111,"minecraft:chain":6,"minecraft:acacia_sapling":4,"minecraft:nether_wart_block":140,"minecraft:wheat":94,"minecraft:tnt":9,"minecraft:warped_fungus":2,"minecraft:stone_brick_stairs":7,"minecraft:grass":52,"minecraft:oak_log":110,"minecraft:acacia_fence":25,"minecraft:sand":195,"minecraft:dirt":321,"minecraft:smooth_basalt":12,"minecraft:stonecutter":1,"minecraft:netherrack":1135,"minecraft:oak_leaves":10,"minecraft:deepslate":418,"minecraft:yellow_terracotta":67,"minecraft:nether_gold_ore":15,"minecraft:diamond_ore":49,"minecraft:tuff":64,"minecraft:dark_oak_leaves":2,"minecraft:deepslate_diamond_ore":2,"minecraft:dark_oak_log":81,"minecraft:nether_bricks":133,"minecraft:crimson_roots":32,"minecraft:weeping_vines":12,"minecraft:spruce_leaves":15,"minecraft:acacia_slab":7,"minecraft:sandstone":41,"minecraft:crimson_stem":21,"minecraft:hay_block":2,"minecraft:redstone_ore":258,"minecraft:furnace":7,"minecraft:chiseled_sandstone":1,"minecraft:acacia_stairs":2,"minecraft:andesite":130,"minecraft:stripped_spruce_log":1,"minecraft:nether_brick_fence":13,"minecraft:deepslate_iron_ore":68,"minecraft:shroomlight":6,"minecraft:rail":2,"minecraft:stone":3988,"minecraft:acacia_leaves":146,"minecraft:glass_pane":7,"minecraft:soul_sand":31,"minecraft:crafting_table":3,"minecraft:rose_bush":6,"minecraft:tall_grass":3,"minecraft:deepslate_coal_ore":79,"minecraft:lapis_ore":37,"minecraft:deepslate_gold_ore":13,"minecraft:diorite":81,"minecraft:red_terracotta":66,"minecraft:coarse_dirt":163,"minecraft:spruce_log":109,"minecraft:coal_ore":383,"minecraft:sunflower":13,"minecraft:gravel":28,"minecraft:flower_pot":1,"minecraft:cracked_stone_bricks":1,"minecraft:cobweb":29,"minecraft:brown_terracotta":83,"minecraft:terracotta":1,"minecraft:acacia_planks":25,"minecraft:stone_bricks":20,"minecraft:gold_ore":55},"minecraft:picked_up":{"minecraft:iron_chestplate":5,"minecraft:wheat":102,"minecraft:nether_brick_fence":13,"minecraft:flower_pot":11,"minecraft:anvil":2,"minecraft:diamond_sword":1,"minecraft:enchanted_book":6,"minecraft:stone_brick_stairs":14,"minecraft:golden_sword":1,"minecraft:amethyst_block":19,"minecraft:string":131,"minecraft:soul_soil":23,"minecraft:cooked_salmon":6,"minecraft:iron_leggings":3,"minecraft:sticky_piston":3,"minecraft:shroomlight":6,"minecraft:gold_nugget":66,"minecraft:cobbled_deepslate":412,"minecraft:bucket":1,"minecraft:rose_bush":16,"minecraft:calcite":99,"minecraft:iron_pickaxe":4,"minecraft:melon_slice":81,"minecraft:furnace":13,"minecraft:iron_boots":2,"minecraft:golden_helmet":1,"minecraft:stick":169,"minecraft:acacia_fence":26,"minecraft:brown_terracotta":99,"minecraft:oak_fence":7,"minecraft:torch":112,"minecraft:acacia_log":168,"minecraft:sandstone_wall":1,"minecraft:porkchop":24,"minecraft:diorite":62,"minecraft:cactus":16,"minecraft:rotten_flesh":121,"minecraft:white_terracotta":130,"minecraft:blaze_rod":8,"minecraft:obsidian":7,"minecraft:cobblestone":4387,"minecraft:magma_block":3,"minecraft:feather":3,"minecraft:iron_door":8,"minecraft:andesite":180,"minecraft:jungle_log":20,"minecraft:acacia_leaves":90,"minecraft:potato":1,"minecraft:flint":2,"minecraft:tuff":42,"minecraft:lapis_lazuli":247,"minecraft:dirt":610,"minecraft:name_tag":2,"minecraft:glass":6,"minecraft:bone":98,"minecraft:acacia_planks":25,"minecraft:stonecutter":1,"minecraft:bow":7,"minecraft:wheat_seeds":404,"minecraft:raw_gold":66,"minecraft:rabbit":1,"minecraft:glowstone_dust":45,"minecraft:oak_planks":27,"minecraft:ghast_tear":1,"minecraft:cooked_porkchop":37,"minecraft:sand":522,"minecraft:stripped_spruce_log":1,"minecraft:cyan_bed":1,"minecraft:acacia_stairs":4,"minecraft:grass_block":1,"minecraft:dark_oak_log":81,"minecraft:chiseled_sandstone":3,"minecraft:red_terracotta":75,"minecraft:light_gray_terracotta":128,"minecraft:diamond":60,"minecraft:granite":85,"minecraft:grass":2,"minecraft:golden_apple":5,"minecraft:emerald":3,"minecraft:golden_horse_armor":1,"minecraft:bread":44,"minecraft:oak_sapling":43,"minecraft:netherrack":1017,"minecraft:crimson_roots":33,"minecraft:diamond_pickaxe":2,"minecraft:cocoa_beans":11,"minecraft:coarse_dirt":278,"minecraft:crafting_table":4,"minecraft:chicken":3,"minecraft:nether_wart":49,"minecraft:golden_pickaxe":1,"minecraft:chain":17,"minecraft:iron_axe":3,"minecraft:item_frame":2,"minecraft:iron_shovel":1,"minecraft:glass_pane":45,"minecraft:cracked_stone_bricks":2,"minecraft:beef":42,"minecraft:poppy":1,"minecraft:light_gray_wool":1,"minecraft:sugar_cane":66,"minecraft:chest":25,"minecraft:egg":9,"minecraft:dark_oak_sapling":18,"minecraft:raw_iron":559,"minecraft:sandstone":120,"minecraft:stone":2,"minecraft:oak_door":2,"minecraft:glow_item_frame":2,"minecraft:fire_charge":2,"minecraft:white_dye":2,"minecraft:redstone":1386,"minecraft:netherite_pickaxe":2,"minecraft:iron_horse_armor":1,"minecraft:stone_pressure_plate":3,"minecraft:tnt":18,"minecraft:arrow":72,"minecraft:weeping_vines":34,"minecraft:golden_hoe":2,"minecraft:nether_bricks":129,"minecraft:shears":1,"minecraft:hay_block":67,"minecraft:yellow_terracotta":73,"minecraft:saddle":1,"minecraft:glistering_melon_slice":7,"minecraft:glow_berries":13,"minecraft:mutton":21,"minecraft:rail":11,"minecraft:white_wool":13,"minecraft:oxeye_daisy":25,"minecraft:glow_ink_sac":35,"minecraft:crimson_stem":21,"minecraft:salmon":1,"minecraft:cut_sandstone":34,"minecraft:leather":24,"minecraft:filled_map":1,"minecraft:crimson_fungus":1,"minecraft:oak_log":102,"minecraft:golden_boots":2,"minecraft:nether_wart_block":136,"minecraft:gunpowder":73,"minecraft:cooked_mutton":7,"minecraft:smooth_sandstone":4,"minecraft:apple":6,"minecraft:stone_bricks":24,"minecraft:heart_of_the_sea":1,"minecraft:rabbit_hide":1,"minecraft:iron_ingot":16,"minecraft:iron_sword":1,"minecraft:acacia_sapling":44,"minecraft:soul_sand":29,"minecraft:book":4,"minecraft:tropical_fish_bucket":1,"minecraft:smooth_basalt":15,"minecraft:warped_fungus":2,"minecraft:quartz":35,"minecraft:gravel":31,"minecraft:spruce_sapling":13,"minecraft:white_bed":5,"minecraft:spruce_log":109,"minecraft:crying_obsidian":1,"minecraft:spider_eye":10,"minecraft:lime_dye":1,"minecraft:iron_helmet":2,"minecraft:gray_wool":2,"minecraft:terracotta":2,"minecraft:melon_seeds":47,"minecraft:acacia_slab":14,"minecraft:black_wool":2,"minecraft:stripped_dark_oak_log":1,"minecraft:coal":606,"minecraft:sunflower":34,"minecraft:ender_pearl":4},"minecraft:broken":{"minecraft:golden_helmet":1,"minecraft:iron_shovel":2,"minecraft:stone_pickaxe":4,"minecraft:diamond_pickaxe":3,"minecraft:stone_axe":1,"minecraft:stone_shovel":3,"minecraft:stone_sword":1,"minecraft:iron_axe":2,"minecraft:iron_pickaxe":9,"minecraft:golden_pickaxe":1},"minecraft:dropped":{"minecraft:lapis_lazuli":5,"minecraft:cooked_beef":4,"minecraft:glow_ink_sac":2,"minecraft:diamond":1,"minecraft:cooked_porkchop":8,"minecraft:saddle":2,"minecraft:flint":2,"minecraft:dirt":3,"minecraft:sand":64,"minecraft:tropical_fish_bucket":1,"minecraft:bone":2,"minecraft:cobbled_deepslate":70,"minecraft:oak_planks":26,"minecraft:glass":27,"minecraft:stone_brick_stairs":5,"minecraft:netherrack":4,"minecraft:bread":10,"minecraft:water_bucket":2,"minecraft:netherite_pickaxe":2,"minecraft:iron_helmet":1,"minecraft:cobblestone":12,"minecraft:granite":10,"minecraft:acacia_log":24,"minecraft:coal":1,"minecraft:stick":64,"minecraft:lava_bucket":1,"minecraft:diorite":1,"minecraft:torch":13,"minecraft:iron_leggings":1,"minecraft:string":11,"minecraft:smooth_basalt":2,"minecraft:tuff":24,"minecraft:raw_iron":4,"minecraft:iron_boots":1,"minecraft:white_terracotta":2,"minecraft:potato":1,"minecraft:shield":1,"minecraft:diamond_pickaxe":1,"minecraft:iron_chestplate":3,"minecraft:andesite":2,"minecraft:sandstone":17,"minecraft:bow":4,"minecraft:wooden_pickaxe":1,"minecraft:magma_block":3},"minecraft:killed":{"minecraft:cave_spider":1,"minecraft:zombified_piglin":2,"minecraft:spider":20,"minecraft:skeleton":50,"minecraft:chicken":1,"minecraft:pig":5,"minecraft:zombie_villager":1,"minecraft:creeper":8,"minecraft:sheep":14,"minecraft:zombie":24,"minecraft:ghast":1,"minecraft:blaze":18,"minecraft:cow":20,"minecraft:horse":1,"minecraft:husk":7,"minecraft:hoglin":11,"minecraft:wither_skeleton":1,"minecraft:villager":1,"minecraft:enderman":1},"minecraft:used":{"minecraft:iron_shovel":689,"minecraft:chest":44,"minecraft:shield":40,"minecraft:white_terracotta":89,"minecraft:stone":157,"minecraft:nether_bricks":56,"minecraft:acacia_sapling":17,"minecraft:weeping_vines":33,"minecraft:obsidian":3,"minecraft:glass":32,"minecraft:stone_brick_stairs":66,"minecraft:stone_bricks":35,"minecraft:item_frame":20,"minecraft:golden_sword":2,"minecraft:bow":89,"minecraft:hay_block":2,"minecraft:furnace":31,"minecraft:acacia_fence":124,"minecraft:egg":1,"minecraft:diorite":1,"minecraft:oak_planks":77,"minecraft:stone_pickaxe":557,"minecraft:wooden_pickaxe":47,"minecraft:sugar_cane":63,"minecraft:glow_berries":14,"minecraft:sand":6,"minecraft:yellow_terracotta":61,"minecraft:blast_furnace":2,"minecraft:acacia_leaves":90,"minecraft:shears":90,"minecraft:acacia_door":1,"minecraft:cyan_bed":1,"minecraft:melon_slice":81,"minecraft:string":5,"minecraft:bread":55,"minecraft:red_terracotta":57,"minecraft:iron_door":1,"minecraft:nether_wart_block":121,"minecraft:diamond_sword":675,"minecraft:grindstone":1,"minecraft:chain":13,"minecraft:coarse_dirt":108,"minecraft:bone_meal":98,"minecraft:golden_pickaxe":32,"minecraft:rose_bush":11,"minecraft:enchanting_table":1,"minecraft:stone_sword":135,"minecraft:flint_and_steel":2,"minecraft:stone_shovel":394,"minecraft:redstone":8,"minecraft:cooked_salmon":6,"minecraft:cooked_chicken":4,"minecraft:netherrack":534,"minecraft:torch":214,"minecraft:dirt":355,"minecraft:anvil":1,"minecraft:salmon_bucket":1,"minecraft:granite":1,"minecraft:shroomlight":6,"minecraft:iron_hoe":180,"minecraft:brown_terracotta":67,"minecraft:iron_axe":621,"minecraft:acacia_slab":32,"minecraft:crimson_planks":16,"minecraft:beef":3,"minecraft:soul_soil":23,"minecraft:cooked_beef":25,"minecraft:cobbled_deepslate":41,"minecraft:acacia_planks":331,"minecraft:crimson_stem":16,"minecraft:calcite":83,"minecraft:wheat_seeds":100,"minecraft:cooked_mutton":34,"minecraft:water_bucket":136,"minecraft:amethyst_block":6,"minecraft:cut_sandstone":16,"minecraft:stonecutter":1,"minecraft:cracked_stone_bricks":1,"minecraft:glow_item_frame":2,"minecraft:crafting_table":6,"minecraft:white_bed":5,"minecraft:smoker":1,"minecraft:oak_log":64,"minecraft:ender_eye":5,"minecraft:diamond_pickaxe":5705,"minecraft:flower_pot":11,"minecraft:acacia_stairs":18,"minecraft:oxeye_daisy":17,"minecraft:iron_pickaxe":2243,"minecraft:stone_axe":103,"minecraft:cobblestone":596,"minecraft:porkchop":2,"minecraft:cooked_porkchop":19,"minecraft:bucket":140,"minecraft:glass_pane":71}},"DataVersion":2730}